basemigrator/__init__.py
basemigrator/changelog_reader.py
basemigrator-0.1.3.dist-info/LICENSE
basemigrator-0.1.3.dist-info/METADATA
basemigrator-0.1.3.dist-info/WHEEL
basemigrator-0.1.3.dist-info/top_level.txt
basemigrator-0.1.3.dist-info/RECORD
