Metadata-Version: 2.1
Name: basemigrator
Version: 0.1.3
Summary: UNKNOWN
Home-page: https://github.com/EduardoThums/basemigrator
Author: Eduardo Cristiano Thums
Author-email: eduardocristiano01@gmail.com
License: MIT
Project-URL: Changelog, https://github.com/EduardoThums/basemigrator/blob/main/CHANGELOG.md
Platform: UNKNOWN
Classifier: License :: OSI Approved :: MIT License
Classifier: Topic :: Database
Classifier: Programming Language :: Python :: 3.7
Classifier: Operating System :: POSIX
Requires-Python: >=3.7
License-File: LICENSE
Requires-Dist: PyYAML (>=6.0)
Provides-Extra: mysql
Requires-Dist: PyMySQL (>=1.0.2) ; extra == 'mysql'
Provides-Extra: postgresql
Requires-Dist: psycopg2-binary (==2.8.6) ; extra == 'postgresql'
